network_call_analyzer_mcp/__init__.py
network_call_analyzer_mcp/__main__.py
network_call_analyzer_mcp/server.py
network_call_analyzer-0.1.0.dist-info/METADATA
network_call_analyzer-0.1.0.dist-info/WHEEL
network_call_analyzer-0.1.0.dist-info/entry_points.txt
network_call_analyzer-0.1.0.dist-info/licenses/LICENSE
network_call_analyzer-0.1.0.dist-info/RECORD
