Metadata-Version: 2.4
Name: network-call-analyzer
Version: 0.1.0
Summary: A Model Context Protocol server providing tools to analyze network traffic for a given URL using Playwright.
Author: Anthropic, PBC.
Maintainer-email: Your Name <your.email@example.com>
License: MIT
License-File: LICENSE
Keywords: automation,llm,mcp,network,playwright
Classifier: Development Status :: 3 - Alpha
Classifier: Intended Audience :: Developers
Classifier: License :: OSI Approved :: MIT License
Classifier: Programming Language :: Python :: 3
Classifier: Programming Language :: Python :: 3.11
Requires-Python: >=3.10
Requires-Dist: mcp>=1.1.3
Requires-Dist: playwright>=1.40
Requires-Dist: pydantic>=2.0.0
